dawnet_cli/__init__.py
dawnet_cli/api.py
dawnet_cli/builder.py
dawnet_cli/cli.py
dawnet_cli/containers.py
dawnet_cli/models.py
dawnet_cli/persistence.py
dawnet_cli-0.0.1.dist-info/LICENSE
dawnet_cli-0.0.1.dist-info/METADATA
dawnet_cli-0.0.1.dist-info/WHEEL
dawnet_cli-0.0.1.dist-info/entry_points.txt
dawnet_cli-0.0.1.dist-info/top_level.txt
dawnet_cli-0.0.1.dist-info/RECORD
