Metadata-Version: 2.1
Name: dawnet-cli
Version: 0.0.1
Summary: A python CLI used to manage DAWnet remotes
Author: Steve Hiehn
Author-email: stevehiehn@gmail.com
License: GPL-3.0
Classifier: Programming Language :: Python :: 3
Classifier: License :: OSI Approved :: GNU General Public License v3 (GPLv3)
License-File: LICENSE
Requires-Dist: click
Requires-Dist: docker
Requires-Dist: questionary
Requires-Dist: urllib3
Requires-Dist: requests
Requires-Dist: appdirs
